PyRandomLoop/__init__.py
PyRandomLoop/core/__init__.py
PyRandomLoop/core/rpm.py
PyRandomLoop/core/utils.py
PyRandomLoop/tests/__init__.py
PyRandomLoop/tests/benchmark.py
PyRandomLoop/tests/test.py
PyRandomLoop-0.2.0.dist-info/METADATA
PyRandomLoop-0.2.0.dist-info/WHEEL
PyRandomLoop-0.2.0.dist-info/top_level.txt
PyRandomLoop-0.2.0.dist-info/RECORD
