Metadata-Version: 2.1
Name: PyRandomLoop
Version: 0.2.0
Summary: Provides a simulation framework for a random loop model in statistical mechanics, including initialization, simulation, and visualization capabilities.
Author: Lorenzo Gregoris
Author-email: lorenzo.gregoris@gmail.com
License: MIT
Classifier: Programming Language :: Python :: 3
Classifier: License :: OSI Approved :: MIT License
Classifier: Operating System :: OS Independent
Requires-Python: >=3.9
